annotated_logger/__init__.py
annotated_logger/filter.py
annotated_logger/mocks.py
annotated_logger/plugins.py
annotated_logger/py.typed
annotated_logger-1.3.3.dist-info/METADATA
annotated_logger-1.3.3.dist-info/WHEEL
annotated_logger-1.3.3.dist-info/entry_points.txt
annotated_logger-1.3.3.dist-info/licenses/LICENSE.txt
annotated_logger-1.3.3.dist-info/RECORD
