Metadata-Version: 2.4
Name: annotated-logger
Version: 1.3.3
Summary: A decorator that logs the start and end of a function as well as providing an optional logger with annotations
Project-URL: Homepage, https://github.com/github/annotated-logger
Author-email: Vuln Mgmt Eng <security+vulnmgmteng@github.com>
License-Expression: MIT
License-File: LICENSE.txt
Keywords: annotation,decorator,logging
Requires-Python: >=3.10
Requires-Dist: makefun
Requires-Dist: pychoir
Requires-Dist: python-json-logger>=3.1.0
Requires-Dist: requests
